MANIFEST.in
README.rst
setup.py
docs/HISTORY.txt
docs/LICENSE.GPL
docs/LICENSE.txt
ftw/__init__.py
ftw.pdfgenerator.egg-info/PKG-INFO
ftw.pdfgenerator.egg-info/SOURCES.txt
ftw.pdfgenerator.egg-info/dependency_links.txt
ftw.pdfgenerator.egg-info/entry_points.txt
ftw.pdfgenerator.egg-info/namespace_packages.txt
ftw.pdfgenerator.egg-info/not-zip-safe
ftw.pdfgenerator.egg-info/requires.txt
ftw.pdfgenerator.egg-info/top_level.txt
ftw/pdfgenerator/__init__.py
ftw/pdfgenerator/assembler.py
ftw/pdfgenerator/babel.py
ftw/pdfgenerator/builder.py
ftw/pdfgenerator/config.py
ftw/pdfgenerator/configure.zcml
ftw/pdfgenerator/customization.py
ftw/pdfgenerator/exceptions.py
ftw/pdfgenerator/interfaces.py
ftw/pdfgenerator/templating.py
ftw/pdfgenerator/testing.py
ftw/pdfgenerator/utils.py
ftw/pdfgenerator/view.py
ftw/pdfgenerator/browser/__init__.py
ftw/pdfgenerator/browser/configure.zcml
ftw/pdfgenerator/browser/export_pdf.pt
ftw/pdfgenerator/browser/standalone.py
ftw/pdfgenerator/browser/views.py
ftw/pdfgenerator/html2latex/__init__.py
ftw/pdfgenerator/html2latex/converter.py
ftw/pdfgenerator/html2latex/patterns.py
ftw/pdfgenerator/html2latex/subconverter.py
ftw/pdfgenerator/html2latex/utils.py
ftw/pdfgenerator/html2latex/wrapper.py
ftw/pdfgenerator/html2latex/subconverters/__init__.py
ftw/pdfgenerator/html2latex/subconverters/footnote.py
ftw/pdfgenerator/html2latex/subconverters/htmlentities.py
ftw/pdfgenerator/html2latex/subconverters/hyperlink.py
ftw/pdfgenerator/html2latex/subconverters/listing.py
ftw/pdfgenerator/html2latex/subconverters/table.py
ftw/pdfgenerator/html2latex/subconverters/textformatting.py
ftw/pdfgenerator/html2latex/subconverters/url.py
ftw/pdfgenerator/layout/__init__.py
ftw/pdfgenerator/layout/baselayout.py
ftw/pdfgenerator/layout/customizable.py
ftw/pdfgenerator/layout/makolayout.py
ftw/pdfgenerator/locales/ftw.pdfgenerator.pot
ftw/pdfgenerator/locales/de/LC_MESSAGES/ftw.pdfgenerator.po
ftw/pdfgenerator/locales/fr/LC_MESSAGES/ftw.pdfgenerator.po
ftw/pdfgenerator/resources/umlaut.ist
ftw/pdfgenerator/tests/__init__.py
ftw/pdfgenerator/tests/base.py
ftw/pdfgenerator/tests/example.py
ftw/pdfgenerator/tests/test.zcml
ftw/pdfgenerator/tests/test_assembler.py
ftw/pdfgenerator/tests/test_babel.py
ftw/pdfgenerator/tests/test_base_layout.py
ftw/pdfgenerator/tests/test_builder.py
