Metadata-Version: 2.1
Name: ftw.pdfgenerator
Version: 1.6.7
Summary: A library for generating PDF representations of Plone objects with LaTeX.
Home-page: https://github.com/4teamwork/ftw.pdfgenerator
Author: 4teamwork AG
Author-email: mailto:info@4teamwork.ch
License: GPL2
Keywords: ftw pdf generator
Platform: UNKNOWN
Classifier: Environment :: Web Environment
Classifier: Framework :: Plone
Classifier: Framework :: Plone :: 4.3
Classifier: Framework :: Plone :: 5.1
Classifier: Intended Audience :: Developers
Classifier: License :: OSI Approved :: GNU General Public License (GPL)
Classifier: Programming Language :: Python
Classifier: Topic :: Software Development :: Libraries :: Python Modules
Provides-Extra: tests
